LICENSE
README.md
setup.py
tap_workday_raas/__init__.py
tap_workday_raas/client.py
tap_workday_raas/discover.py
tap_workday_raas/sync.py
tap_workday_raas/transform.py
tap_workday_raas.egg-info/PKG-INFO
tap_workday_raas.egg-info/SOURCES.txt
tap_workday_raas.egg-info/dependency_links.txt
tap_workday_raas.egg-info/entry_points.txt
tap_workday_raas.egg-info/requires.txt
tap_workday_raas.egg-info/top_level.txt