Metadata-Version: 2.1
Name: tap-workday-raas
Version: 1.0.1
Summary: Singer.io tap for extracting data
Home-page: http://singer.io
Author: Stitch
License: UNKNOWN
Platform: UNKNOWN
Classifier: Programming Language :: Python :: 3 :: Only
Provides-Extra: dev
